README
setup.cfg
setup.py
bin/weblog
weblog/__init__.py
weblog/_jinja_environment.py
weblog/date.py
weblog/html_full_url.py
weblog/html_to_xhtml.py
weblog/listing.py
weblog/load.py
weblog/markdown2.py
weblog/post.py
weblog/publish.py
weblog/rfc3339.py
weblog/utf8_html_parser.py
weblog/utils.py
weblog.egg-info/PKG-INFO
weblog.egg-info/SOURCES.txt
weblog.egg-info/dependency_links.txt
weblog.egg-info/not-zip-safe
weblog.egg-info/requires.txt
weblog.egg-info/top_level.txt