Metadata-Version: 1.1
Name: weblog
Version: 1.1
Summary: Simple blog publisher. It reads structured text files and generates static HTML / RSS files. Weblog aims to be simple and robust.
Home-page: http://henry.precheur.org/weblog/
Author: Henry Precheur
Author-email: henry@precheur.org
License: ISCL
Keywords: weblog blog journal diary atom
Platform: UNKNOWN
Classifier: Development Status :: 5 - Production/Stable
Classifier: Topic :: Internet :: WWW/HTTP :: Dynamic Content :: News/Diary
Classifier: Intended Audience :: End Users/Desktop
Classifier: Programming Language :: Python
Requires: Jinja2 (>=2.0)
